<?xml version="1.0" encoding="UTF-8"?>

<groups>

<group name="G1">
<channel name="SR_PS_QM1:current:ai">QM1:ai</channel>
<channel name="SR_PS_QM2:current:ai">QM2:ai</channel>
<channel name="SR_PS_QM3:current:ai">QM3:ai</channel>
<channel name="SR_PS_QM4:current:ai">QM4:ai</channel>
<channel name="SR_PS_QM5:current:ai">QM5:ai</channel>
<channel name="SR_PS_QM6:current:ai">QM6:ai</channel>
<channel name="SR_PS_QM7:current:ai">QM7:ai</channel>
<channel name="SR_PS_QM8:current:ai">QM8:ai</channel>
<channel name="SR_PS_QM9:current:ai">QM9:ai</channel>
<channel name="SR_PS_QM10:current:ai">QM10:ai</channel>
<channel name="SR_PS_QM11:current:ai">QM11:ai</channel>
<channel name="SR_PS_QM12:current:ai">QM12:ai</channel>
<channel name="SR_PS_QM13:current:ai">QM13:ai</channel>
<channel name="SR_PS_QM14:current:ai">QM14:ai</channel>
<channel name="SR_PS_QM15:current:ai">QM15:ai</channel>
<channel name="SR_PS_QM16:current:ai">QM16:ai</channel>
<channel name="SR_PS_QM17:current:ai">QM17:ai</channel>
<channel name="SR_PS_QM18:current:ai">QM18:ai</channel>
<channel name="SR_PS_QM19:current:ai">QM19:ai</channel>
<channel name="SR_PS_QM20:current:ai">QM20:ai</channel>
<channel name="SR_PS_QM21:current:ai">QM21:ai</channel>
<channel name="SR_PS_QM22:current:ai">QM22:ai</channel>
<channel name="SR_PS_QM23:current:ai">QM23:ai</channel>
<channel name="SR_PS_QM24:current:ai">QM24:ai</channel>
<channel name="SR_PS_QM25:current:ai">QM25:ai</channel>
<channel name="SR_PS_QM26:current:ai">QM26:ai</channel>
<channel name="SR_PS_QM27:current:ai">QM27:ai</channel>
<channel name="SR_PS_QM28:current:ai">QM28:ai</channel>
<channel name="SR_PS_QM29:current:ai">QM29:ai</channel>
<channel name="SR_PS_QM30:current:ai">QM30:ai</channel>
<channel name="SR_PS_QM31:current:ai">QM31:ai</channel>
<channel name="SR_PS_QM32:current:ai">QM32:ai</channel>
<channel name="SR_PS_QM1:current:ao">QM1:ao</channel>
<channel name="SR_PS_QM2:current:ao">QM2:ao</channel>
<channel name="SR_PS_QM3:current:ao">QM3:ao</channel>
<channel name="SR_PS_QM4:current:ao">QM4:ao</channel>
<channel name="SR_PS_QM5:current:ao">QM5:ao</channel>
<channel name="SR_PS_QM6:current:ao">QM6:ao</channel>
<channel name="SR_PS_QM7:current:ao">QM7:ao</channel>
<channel name="SR_PS_QM8:current:ao">QM8:ao</channel>
<channel name="SR_PS_QM9:current:ao">QM9:ao</channel>
<channel name="SR_PS_QM10:current:ao">QM10:ao</channel>
<channel name="SR_PS_QM11:current:ao">QM11:ao</channel>
<channel name="SR_PS_QM12:current:ao">QM12:ao</channel>
<channel name="SR_PS_QM13:current:ao">QM13:ao</channel>
<channel name="SR_PS_QM14:current:ao">QM14:ao</channel>
<channel name="SR_PS_QM15:current:ao">QM15:ao</channel>
<channel name="SR_PS_QM16:current:ao">QM16:ao</channel>
<channel name="SR_PS_QM17:current:ao">QM17:ao</channel>
<channel name="SR_PS_QM18:current:ao">QM18:ao</channel>
<channel name="SR_PS_QM19:current:ao">QM19:ao</channel>
<channel name="SR_PS_QM20:current:ao">QM20:ao</channel>
<channel name="SR_PS_QM21:current:ao">QM21:ao</channel>
<channel name="SR_PS_QM22:current:ao">QM22:ao</channel>
<channel name="SR_PS_QM23:current:ao">QM23:ao</channel>
<channel name="SR_PS_QM24:current:ao">QM24:ao</channel>
<channel name="SR_PS_QM25:current:ao">QM25:ao</channel>
<channel name="SR_PS_QM26:current:ao">QM26:ao</channel>
<channel name="SR_PS_QM27:current:ao">QM27:ao</channel>
<channel name="SR_PS_QM28:current:ao">QM28:ao</channel>
<channel name="SR_PS_QM29:current:ao">QM29:ao</channel>
<channel name="SR_PS_QM30:current:ao">QM30:ao</channel>
<channel name="SR_PS_QM31:current:ao">QM31:ao</channel>
<channel name="SR_PS_QM32:current:ao">QM32:ao</channel>
</group>

<group name="G2">
<unit >Current(A)</unit>
</group>

<group name="G3">
<ChartTitle>SR-PS</ChartTitle>
</group>

</groups>

